COPYING
COPYING.lesser
MANIFEST.in
NOTICE
README.md
requirements.txt
setup.py
Pyrography.egg-info/PKG-INFO
Pyrography.egg-info/SOURCES.txt
Pyrography.egg-info/dependency_links.txt
Pyrography.egg-info/not-zip-safe
Pyrography.egg-info/requires.txt
Pyrography.egg-info/top_level.txt
compiler/__init__.py
compiler/api/__init__.py
compiler/api/compiler.py
compiler/api/source/auth_key.tl
compiler/api/source/main_api.tl
compiler/api/source/sys_msgs.tl
compiler/api/template/combinator.txt
compiler/api/template/type.txt
compiler/docs/__init__.py
compiler/docs/compiler.py
compiler/docs/template/page.txt
compiler/docs/template/toctree.txt
compiler/errors/__init__.py
compiler/errors/compiler.py
compiler/errors/sort.py
compiler/errors/source/303_SEE_OTHER.tsv
compiler/errors/source/400_BAD_REQUEST.tsv
compiler/errors/source/401_UNAUTHORIZED.tsv
compiler/errors/source/403_FORBIDDEN.tsv
compiler/errors/source/406_NOT_ACCEPTABLE.tsv
compiler/errors/source/420_FLOOD.tsv
compiler/errors/source/500_INTERNAL_SERVER_ERROR.tsv
compiler/errors/source/503_SERVICE_UNAVAILABLE.tsv
compiler/errors/template/class.txt
compiler/errors/template/sub_class.txt
pyrography/__init__.py
pyrography/client.py
pyrography/dispatcher.py
pyrography/emoji.py
pyrography/file_id.py
pyrography/filters.py
pyrography/mime_types.py
pyrography/py.typed
pyrography/sync.py
pyrography/utils.py
pyrography/connection/__init__.py
pyrography/connection/connection.py
pyrography/connection/transport/__init__.py
pyrography/connection/transport/tcp/__init__.py
pyrography/connection/transport/tcp/tcp.py
pyrography/connection/transport/tcp/tcp_abridged.py
pyrography/connection/transport/tcp/tcp_abridged_o.py
pyrography/connection/transport/tcp/tcp_full.py
pyrography/connection/transport/tcp/tcp_intermediate.py
pyrography/connection/transport/tcp/tcp_intermediate_o.py
pyrography/crypto/__init__.py
pyrography/crypto/aes.py
pyrography/crypto/mtproto.py
pyrography/crypto/prime.py
pyrography/crypto/rsa.py
pyrography/enums/__init__.py
pyrography/enums/auto_name.py
pyrography/enums/chat_action.py
pyrography/enums/chat_event_action.py
pyrography/enums/chat_member_status.py
pyrography/enums/chat_members_filter.py
