Metadata-Version: 2.1
Name: Pyrography
Version: 1.0.0
Summary: A Pyrogram fork inspired by Pyromod & AmanoTeam/Pyrogram.
Home-page: https://github.com/d3cryptofc/pyrography
Download-URL: https://github.com/d3cryptofc/pyrography/releases/latest
Author: Lelzin λ
Author-email: d3cryptofc@gmail.com
License: LGPLv3
Project-URL: Tracker, https://github.com/d3cryptofc/pyrography/issues
Project-URL: Community, https://t.me/forkpyrography
Project-URL: Source, https://github.com/d3cryptofc/pyrography
Project-URL: Documentation, https://docs.pyrogram.org
Keywords: telegram chat messenger mtproto api client library python
Classifier: Development Status :: 5 - Production/Stable
Classifier: Intended Audience :: Developers
Classifier: Natural Language :: English
Classifier: License :: OSI Approved :: GNU Lesser General Public License v3 (LGPLv3)
Classifier: Operating System :: OS Independent
Classifier: Programming Language :: Python
Classifier: Programming Language :: Python :: 3
Classifier: Programming Language :: Python :: 3.7
Classifier: Programming Language :: Python :: 3.8
Classifier: Programming Language :: Python :: 3.9
Classifier: Programming Language :: Python :: 3.10
Classifier: Programming Language :: Python :: 3.11
Classifier: Programming Language :: Python :: Implementation
Classifier: Programming Language :: Python :: Implementation :: CPython
Classifier: Programming Language :: Python :: Implementation :: PyPy
Classifier: Topic :: Internet
Classifier: Topic :: Communications
Classifier: Topic :: Communications :: Chat
Classifier: Topic :: Software Development :: Libraries
Classifier: Topic :: Software Development :: Libraries :: Python Modules
Classifier: Topic :: Software Development :: Libraries :: Application Frameworks
Requires-Python: ~=3.7
License-File: COPYING
License-File: COPYING.lesser
License-File: NOTICE
